README.rst
setup.py
tinycrawler/__init__.py
tinycrawler/__version__.py
tinycrawler/tinycrawler.py
tinycrawler.egg-info/PKG-INFO
tinycrawler.egg-info/SOURCES.txt
tinycrawler.egg-info/dependency_links.txt
tinycrawler.egg-info/requires.txt
tinycrawler.egg-info/top_level.txt
tinycrawler/bloom/__init__.py
tinycrawler/bloom/bloom.py
tinycrawler/cli/__init__.py
tinycrawler/cli/cli.py
tinycrawler/job/__init__.py
tinycrawler/job/filejob.py
tinycrawler/job/job.py
tinycrawler/job/proxyjob.py
tinycrawler/job/robotsjob.py
tinycrawler/job/urljob.py
tinycrawler/log/__init__.py
tinycrawler/log/log.py
tinycrawler/managers/__init__.py
tinycrawler/managers/tinycrawler_manager.py
tinycrawler/process/__init__.py
tinycrawler/process/downloader.py
tinycrawler/process/file_parser.py
tinycrawler/process/parser.py
tinycrawler/process/process_handler.py
tinycrawler/process/url_parser.py
tinycrawler/statistics/__init__.py
tinycrawler/statistics/speed.py
tinycrawler/statistics/statistics.py
tinycrawler/statistics/time.py
tinycrawler/utils/__init__.py
tinycrawler/utils/utils.py