Metadata-Version: 1.1
Name: tinycrawler
Version: 1.7.0
Summary: Small customizable multiprocessing multi-proxy crawler.
Home-page: https://github.com/LucaCappelletti94/tinycrawler
Author: Luca Cappelletti
Author-email: cappelletti.luca94@gmail.com
License: MIT
Platform: UNKNOWN
Classifier: Development Status :: 4 - Beta
Classifier: Intended Audience :: Information Technology
Classifier: Topic :: Scientific/Engineering :: Information Analysis
Classifier: License :: OSI Approved :: MIT License
Classifier: Programming Language :: Python :: 3
